{
  "title": "HEROLL-ヒーロール",
  "short_title": "ヒーロール",
  "chapter_count": 27,
  "url": "https://jmanga.se/read/heroll-ヒーロール-raw/",
  "genres": [
    "バトル・アクション",
    "ファンタジー"
  ],
  "status": "",
  "summary": "HEROLL-ヒーロール raw,HEROLL-ヒーロール zip,HEROLL-ヒーロール manga\t\t\t\t\t\t\t\t潤香が恋する、無口なクラスメイト・犬神匡（きょう）は、実はキモオタ荒川浅（せん）と共に大人気アニメキャラのミラクル☆聖子に変身し、零病（サイレントウイルス）をやっつけるヒーローだった！（著者名：へろ/初出：GANMA!1～7話掲載分）",
  "image": "https://imgjm.jmanga.ac/thumb/300/upload/2024/11/ec38dbe088118a1053081f131daaa1fb.jpeg",
  "related_manga": [
    {
      "url": "https://jmanga.se/read/エゴ・エリス-剣奴の血-raw/",
      "title": "エゴ・エリス－剣奴の血－"
    },
    {
      "url": "https://jmanga.se/read/だから僕達は幼馴染を辞めた。-raw/",
      "title": "だから僕達は幼馴染を辞めた。"
    },
    {
      "url": "https://jmanga.se/read/はじめしゃちょーのユーチューバーな日常-raw/",
      "title": "はじめしゃちょーのユーチューバーな日常"
    },
    {
      "url": "https://jmanga.se/read/やきもの九十九の素敵な食卓-raw/",
      "title": "やきもの九十九の素敵な食卓"
    },
    {
      "url": "https://jmanga.se/read/ひのきのダンジョン-raw/",
      "title": "ひのきのダンジョン"
    },
    {
      "url": "https://jmanga.se/read/金田一３７歳の事件簿-raw/",
      "title": "金田一３７歳の事件簿"
    },
    {
      "url": "https://jmanga.se/read/魔女の守人-raw/",
      "title": "魔女の守人"
    },
    {
      "url": "https://jmanga.se/read/小林少年と不逞の怪人-raw/",
      "title": "小林少年と不逞の怪人"
    },
    {
      "url": "https://jmanga.se/read/ホーキーベカコン-raw/",
      "title": "ホーキーベカコン"
    },
    {
      "url": "https://jmanga.se/read/黄昏星のスイとネリ-raw/",
      "title": "黄昏星のスイとネリ"
    },
    {
      "url": "https://jmanga.se/read/高校事変-raw/",
      "title": "高校事変"
    },
    {
      "url": "https://jmanga.se/read/御影くんは帰りたい！-raw/",
      "title": "御影くんは帰りたい！"
    },
    {
      "url": "https://jmanga.se/read/まもりママはお喚びじゃないの-～異世界息子反抗記～-raw/",
      "title": "まもりママはお喚びじゃないの!?～異世界息子反抗記～"
    },
    {
      "url": "https://jmanga.se/read/小さいノゾミと大きなユメ-raw/",
      "title": "小さいノゾミと大きなユメ"
    },
    {
      "url": "https://jmanga.se/read/大蜘蛛ちゃんフラッシュ・バック-raw/",
      "title": "大蜘蛛ちゃんフラッシュ・バック"
    }
  ]
}