{
  "title": "ふろラン",
  "short_title": "ふろラン",
  "chapter_count": 13,
  "url": "https://jmanga.se/read/ふろラン-raw/",
  "genres": [
    "スポーツ",
    "陸上・マラソン"
  ],
  "status": "",
  "summary": "ふろラン raw,ふろラン zip,ふろラン manga\t\t\t\t\t\t\t\t「ふろラン」は、お風呂とランニングをテーマにしたガールズコメディ。女子大生の凛は、銭湯に入ろうとしていたところを友人の結衣に「走るよ今から！」と誘われ、説明もないままランニングに連れ出される。「私について来たら気持ちいいことが待ってるよ」という結衣の言葉を信じて、運動不足の体を酷使して走る凛。その先に待ち受ける「気持ちいいこと」とは。",
  "image": "https://imgjm.jmanga.ac/thumb/300/upload/2024/11/144a1f77b19275d90a3210c09ab80792.jpeg",
  "related_manga": [
    {
      "url": "https://jmanga.se/read/令和はなまる学園-raw/",
      "title": "令和はなまる学園"
    },
    {
      "url": "https://jmanga.se/read/だから僕達は幼馴染を辞めた。-raw/",
      "title": "だから僕達は幼馴染を辞めた。"
    },
    {
      "url": "https://jmanga.se/read/まもりママはお喚びじゃないの-～異世界息子反抗記～-raw/",
      "title": "まもりママはお喚びじゃないの!?～異世界息子反抗記～"
    },
    {
      "url": "https://jmanga.se/read/クズ異能【温度を変える者《サーモオペレーター》】の-俺が無双するまで-raw/",
      "title": "クズ異能【温度を変える者《サーモオペレーター》】の 俺が無双するまで"
    },
    {
      "url": "https://jmanga.se/read/めんや-raw/",
      "title": "めんや"
    },
    {
      "url": "https://jmanga.se/read/育てち魔おう！-raw/",
      "title": "育てち魔おう！"
    },
    {
      "url": "https://jmanga.se/read/あやかしメルヒェン-raw/",
      "title": "あやかしメルヒェン"
    },
    {
      "url": "https://jmanga.se/read/金田一３７歳の事件簿-raw/",
      "title": "金田一３７歳の事件簿"
    },
    {
      "url": "https://jmanga.se/read/やきもの九十九の素敵な食卓-raw/",
      "title": "やきもの九十九の素敵な食卓"
    },
    {
      "url": "https://jmanga.se/read/ホームルーム-raw/",
      "title": "ホームルーム"
    },
    {
      "url": "https://jmanga.se/read/ホーキーベカコン-raw/",
      "title": "ホーキーベカコン"
    },
    {
      "url": "https://jmanga.se/read/高校事変-raw/",
      "title": "高校事変"
    },
    {
      "url": "https://jmanga.se/read/ひのきのダンジョン-raw/",
      "title": "ひのきのダンジョン"
    },
    {
      "url": "https://jmanga.se/read/ざ・ふぁぶる-raw/",
      "title": "ざ・ふぁぶる"
    },
    {
      "url": "https://jmanga.se/read/異世界健康食堂-～アラサー栄養士のセカンドライフ～-raw/",
      "title": "異世界健康食堂 ～アラサー栄養士のセカンドライフ～"
    }
  ]
}