{
  "title": "トリニティセブン アナスタシア聖伝",
  "short_title": "アナスタシア",
  "chapter_count": 17,
  "url": "https://jmanga.io/read/トリニティセブン-アナスタシア聖伝-raw/",
  "genres": [
    "ラブストーリー",
    "ラブコメ",
    "ファンタジー",
    "学園",
    "萌え"
  ],
  "status": "",
  "summary": "トリニティセブン アナスタシア聖伝 raw,トリニティセブン アナスタシア聖伝 zip,トリニティセブン アナスタシア聖伝 manga\t\t\t\t\t\t\t\tこれは、恋する聖女の裏切りの物語。\nトリニティセブン最新スピンオフ開幕!",
  "image": "https://imgjm.jmanga.ac/thumb/300/upload/2024/11/768605b019405da7231c4d1a79bf40cb.jpeg",
  "related_manga": [
    {
      "url": "https://jmanga.io/read/トリニティセブン-リヴィジョン-raw/",
      "title": "トリニティセブン　-リヴィジョン"
    },
    {
      "url": "https://jmanga.io/read/トリニティセブン-7人の魔書使い【タテスク】-raw/",
      "title": "トリニティセブン　7人の魔書使い【タテスク】"
    },
    {
      "url": "https://jmanga.io/read/トリニティセブン-7人の魔書使い-raw/",
      "title": "トリニティセブン 7人の魔書使い"
    },
    {
      "url": "https://jmanga.io/read/落ちてるふたり-raw/",
      "title": "落ちてるふたり"
    },
    {
      "url": "https://jmanga.io/read/恋ニ非ズ-raw/",
      "title": "恋ニ非ズ"
    },
    {
      "url": "https://jmanga.io/read/開演のベルでおやすみ-raw/",
      "title": "開演のベルでおやすみ"
    },
    {
      "url": "https://jmanga.io/read/夜になると僕は-raw/",
      "title": "夜になると僕は"
    },
    {
      "url": "https://jmanga.io/read/バカップル-raw/",
      "title": "バカップル"
    },
    {
      "url": "https://jmanga.io/read/はたらかない細胞-raw/",
      "title": "はたらかない細胞"
    },
    {
      "url": "https://jmanga.io/read/とんずらごはん-raw/",
      "title": "とんずらごはん"
    },
    {
      "url": "https://jmanga.io/read/線は、僕を描く-raw/",
      "title": "線は、僕を描く"
    },
    {
      "url": "https://jmanga.io/read/コンビニお嬢さま-raw/",
      "title": "コンビニお嬢さま"
    },
    {
      "url": "https://jmanga.io/read/a-bout-～朝桐大活躍編～-raw/",
      "title": "A-BOUT!!～朝桐大活躍編～"
    },
    {
      "url": "https://jmanga.io/read/エデンの檻-raw/",
      "title": "エデンの檻"
    },
    {
      "url": "https://jmanga.io/read/eat-man-the-main-dish-raw/",
      "title": "EAT-MAN THE MAIN DISH"
    }
  ]
}