{
  "title": "リクドウ",
  "short_title": "リクドウ",
  "chapter_count": 64,
  "url": "https://jmanga.se/read/リクドウ-raw/",
  "genres": [
    "バトル・アクション"
  ],
  "status": "",
  "summary": "リクドウ raw,リクドウ zip,リクドウ manga\t\t\t\t\t\t\t\t父親を失った少年・芥生リクは借金取りの元ボクサー・所沢京介と出会う。理不尽に満ちたこの世界で、人は何をよすがに生き抜くのか。戦うのか。人生という茨の道を歩む芥生リクの破格の拳闘ストーリー！　少年には何もない。その拳以外は。",
  "image": "https://imgjm.jmanga.ac/thumb/300/upload/2024/11/9baf82d4b9f134ab5c367619ab368e61.jpeg",
  "related_manga": [
    {
      "url": "https://jmanga.se/read/解体屋ゲン-raw/",
      "title": "解体屋ゲン"
    },
    {
      "url": "https://jmanga.se/read/高校事変-raw/",
      "title": "高校事変"
    },
    {
      "url": "https://jmanga.se/read/まもりママはお喚びじゃないの-～異世界息子反抗記～-raw/",
      "title": "まもりママはお喚びじゃないの!?～異世界息子反抗記～"
    },
    {
      "url": "https://jmanga.se/read/友達として大好き-raw/",
      "title": "友達として大好き"
    },
    {
      "url": "https://jmanga.se/read/金田一３７歳の事件簿-raw/",
      "title": "金田一３７歳の事件簿"
    },
    {
      "url": "https://jmanga.se/read/セクサロイドにaiをこめて-raw/",
      "title": "セクサロイドにAIをこめて"
    },
    {
      "url": "https://jmanga.se/read/シャドーハウス-カラー版-raw/",
      "title": "シャドーハウス カラー版"
    },
    {
      "url": "https://jmanga.se/read/令和はなまる学園-raw/",
      "title": "令和はなまる学園"
    },
    {
      "url": "https://jmanga.se/read/育てち魔おう！-raw/",
      "title": "育てち魔おう！"
    },
    {
      "url": "https://jmanga.se/read/小さいノゾミと大きなユメ-raw/",
      "title": "小さいノゾミと大きなユメ"
    },
    {
      "url": "https://jmanga.se/read/ホーキーベカコン-raw/",
      "title": "ホーキーベカコン"
    },
    {
      "url": "https://jmanga.se/read/やきもの九十九の素敵な食卓-raw/",
      "title": "やきもの九十九の素敵な食卓"
    },
    {
      "url": "https://jmanga.se/read/異世界健康食堂-～アラサー栄養士のセカンドライフ～-raw/",
      "title": "異世界健康食堂 ～アラサー栄養士のセカンドライフ～"
    },
    {
      "url": "https://jmanga.se/read/だから僕達は幼馴染を辞めた。-raw/",
      "title": "だから僕達は幼馴染を辞めた。"
    },
    {
      "url": "https://jmanga.se/read/黄昏星のスイとネリ-raw/",
      "title": "黄昏星のスイとネリ"
    }
  ]
}