{
  "title": "万能変化メカトロウィーゴ",
  "short_title": "メカトロウィーゴ",
  "chapter_count": 9,
  "url": "https://jmanga.io/read/万能変化メカトロウィーゴ-raw/",
  "genres": [
    "ヒューマンドラマ",
    "ファンタジー"
  ],
  "status": "",
  "summary": "万能変化メカトロウィーゴ raw,万能変化メカトロウィーゴ zip,万能変化メカトロウィーゴ manga\t\t\t\t\t\t\t\tごく普通の街に住む子供たちの日常は、ある異形の出現で崩れ去った。乗る者のあらゆる可能性を増幅するロボに乗り、絶望の未来を取り戻せ。――『ヱヴァンゲリヲン新劇場版シリーズ』で３Dモデリングを担当した小林和史が生み出した人気ロボットキャラクター「メカトロウィーゴ」のオリジナル漫画が誕生！さらになんと世界的メカニックデザイナー・大河原邦男氏オリジナル機体も登場‼",
  "image": "https://imgjm.jmanga.ac/thumb/300/upload/2024/11/b9234956fb4c3f8fab9fedf2238d5618.jpeg",
  "related_manga": [
    {
      "url": "https://jmanga.io/read/trump-raw/",
      "title": "TRUMP"
    },
    {
      "url": "https://jmanga.io/read/乙女高校ボクシング部-raw/",
      "title": "乙女高校ボクシング部"
    },
    {
      "url": "https://jmanga.io/read/はたらかない細胞-raw/",
      "title": "はたらかない細胞"
    },
    {
      "url": "https://jmanga.io/read/eat-man-the-main-dish-raw/",
      "title": "EAT-MAN THE MAIN DISH"
    },
    {
      "url": "https://jmanga.io/read/アンデッドガール・マーダーファルス-raw/",
      "title": "アンデッドガール・マーダーファルス"
    },
    {
      "url": "https://jmanga.io/read/はたらく魔王さまのメシ！-raw/",
      "title": "はたらく魔王さまのメシ！"
    },
    {
      "url": "https://jmanga.io/read/我間乱～gamaran～-raw/",
      "title": "我間乱～GAMARAN～"
    },
    {
      "url": "https://jmanga.io/read/やがて君になる-raw/",
      "title": "やがて君になる"
    },
    {
      "url": "https://jmanga.io/read/紅殻のパンドラ-raw/",
      "title": "紅殻のパンドラ"
    },
    {
      "url": "https://jmanga.io/read/恋ニ非ズ-raw/",
      "title": "恋ニ非ズ"
    },
    {
      "url": "https://jmanga.io/read/a-bout-～朝桐大活躍編～-raw/",
      "title": "A-BOUT!!～朝桐大活躍編～"
    },
    {
      "url": "https://jmanga.io/read/拳児２-raw/",
      "title": "拳児２"
    },
    {
      "url": "https://jmanga.io/read/ふらちな倫理ちゃん-raw/",
      "title": "ふらちな倫理ちゃん"
    },
    {
      "url": "https://jmanga.io/read/線は、僕を描く-raw/",
      "title": "線は、僕を描く"
    },
    {
      "url": "https://jmanga.io/read/エデンの檻-raw/",
      "title": "エデンの檻"
    }
  ]
}