{
  "title": "信友島～良い人でなければ終わり～",
  "short_title": "信友島",
  "chapter_count": 58,
  "url": "https://jmanga.io/read/信友島～良い人でなければ終わり～-raw/",
  "genres": [
    "ヒューマンドラマ"
  ],
  "status": "",
  "summary": "信友島～良い人でなければ終わり～ raw,信友島～良い人でなければ終わり～ zip,信友島～良い人でなければ終わり～ manga\t\t\t\t\t\t\t\t両親を亡くし叔父叔母に虐待を受けて暮らす佐藤は、バイトの先輩・喜多に「信友島」に連れてこられる。信友島は働かずに好きなことができる楽園のような島だが、ひとつだけルールがあった――「隣人の良き人であること」。景色は美しく島民も優しい信友島だが、唯一のルールを破ったときに恐ろしいことが待ちかまえていた――。",
  "image": "https://imgjm.jmanga.ac/thumb/300/upload/2024/11/8e2f6810beb21cf367ad79cfb0ae2755.jpeg",
  "related_manga": [
    {
      "url": "https://jmanga.io/read/開演のベルでおやすみ-raw/",
      "title": "開演のベルでおやすみ"
    },
    {
      "url": "https://jmanga.io/read/コンビニお嬢さま-raw/",
      "title": "コンビニお嬢さま"
    },
    {
      "url": "https://jmanga.io/read/紅殻のパンドラ-raw/",
      "title": "紅殻のパンドラ"
    },
    {
      "url": "https://jmanga.io/read/寄宿学校のジュリエット-raw/",
      "title": "寄宿学校のジュリエット"
    },
    {
      "url": "https://jmanga.io/read/おやすみ睡魔と夜ふかしjk-raw/",
      "title": "おやすみ睡魔と夜ふかしJK"
    },
    {
      "url": "https://jmanga.io/read/夜になると僕は-raw/",
      "title": "夜になると僕は"
    },
    {
      "url": "https://jmanga.io/read/エデンの檻-raw/",
      "title": "エデンの檻"
    },
    {
      "url": "https://jmanga.io/read/バカップル-raw/",
      "title": "バカップル"
    },
    {
      "url": "https://jmanga.io/read/trump-raw/",
      "title": "TRUMP"
    },
    {
      "url": "https://jmanga.io/read/吸血鬼ちゃんx後輩ちゃん-raw/",
      "title": "吸血鬼ちゃん×後輩ちゃん"
    },
    {
      "url": "https://jmanga.io/read/シバトラ-raw/",
      "title": "シバトラ"
    },
    {
      "url": "https://jmanga.io/read/仮面ライダーblack-raw/",
      "title": "仮面ライダーBlack"
    },
    {
      "url": "https://jmanga.io/read/はたらく魔王さまのメシ！-raw/",
      "title": "はたらく魔王さまのメシ！"
    },
    {
      "url": "https://jmanga.io/read/拳児２-raw/",
      "title": "拳児２"
    },
    {
      "url": "https://jmanga.io/read/this-man-その顔を見た者には死を-raw/",
      "title": "This Man その顔を見た者には死を"
    }
  ]
}