{
  "title": "剣任せでレベルアップ",
  "short_title": "剣任せで",
  "chapter_count": 72,
  "url": "https://jmanga.se/read/剣任せでレベルアップ-raw/",
  "genres": [
    "ファンタジー",
    "冒険",
    "フルカラー",
    "アクション",
    "勇者",
    "少年マンガ",
    "独占配信",
    "SMARTOON",
    "Kakao Page Corp."
  ],
  "status": "",
  "summary": "",
  "image": "https://imgjm.jmanga.ac/thumb/300/upload/2024/05/b28a2c509cc621293755fe0fe0ab6d29.jpeg",
  "related_manga": [
    {
      "url": "https://jmanga.se/read/パーフェクト・ガール-raw/",
      "title": "パーフェクト・ガール"
    },
    {
      "url": "https://jmanga.se/read/デッドカンパニー-dead-company-raw/",
      "title": "デッドカンパニー ? Dead Company"
    },
    {
      "url": "https://jmanga.se/read/色即是空の歩き方-raw/",
      "title": "色即是空の歩き方"
    },
    {
      "url": "https://jmanga.se/read/ベスティア-raw/",
      "title": "ベスティア"
    },
    {
      "url": "https://jmanga.se/read/island-狂愛ⅹサバイバルー-raw/",
      "title": "ISLAND-狂愛ⅹサバイバルー"
    },
    {
      "url": "https://jmanga.se/read/ポンコツンデレな幼馴染-raw/",
      "title": "ポンコツンデレな幼馴染"
    },
    {
      "url": "https://jmanga.se/read/じぇいけぇゆ-raw/",
      "title": "じぇいけぇゆ"
    },
    {
      "url": "https://jmanga.se/read/ランドセルと異世界さんぽ-raw/",
      "title": "ランドセルと異世界さんぽ"
    },
    {
      "url": "https://jmanga.se/read/イミグリム-～弱虫悪魔の異世界移住計画～-raw/",
      "title": "イミグリム ～弱虫悪魔の異世界移住計画～"
    },
    {
      "url": "https://jmanga.se/read/final-re-quest-ファイナルリクエスト-raw/",
      "title": "Final Re:Quest ―ファイナルリクエスト―"
    },
    {
      "url": "https://jmanga.se/read/faceless-ダークヒーロー編-raw/",
      "title": "faceless ? ダークヒーロー編"
    },
    {
      "url": "https://jmanga.se/read/名古屋以外全部壊滅-raw/",
      "title": "名古屋以外全部壊滅"
    },
    {
      "url": "https://jmanga.se/read/キン肉マン-38巻以降-、週プレ連載シリーズ-raw/",
      "title": "キン肉マン (38巻以降〜、週プレ連載シリーズ)"
    },
    {
      "url": "https://jmanga.se/read/ストーカー浄化団-stalker-jokers-raw/",
      "title": "ストーカー浄化団 -STALKER JOKERS"
    },
    {
      "url": "https://jmanga.se/read/fate-stay-night-heaven-s-feel-フェイト-ゼロ-raw/",
      "title": "Fate/stay night (Heaven?s Feel) フェイト/ゼロ"
    }
  ]
}