{
  "title": "奪う者 奪われる者 掠夺者剥夺者",
  "short_title": "奪う者 奪われる者",
  "chapter_count": 21,
  "url": "https://jmanga.se/read/奪う者-奪われる者-掠夺者剥夺者-raw/",
  "genres": [
    "ファンタジー",
    "冒険",
    "ハーレム"
  ],
  "status": "",
  "summary": "奪う者 奪われる者 掠夺者剥夺者 raw,奪う者 奪われる者 掠夺者剥夺者 zip,奪う者 奪われる者 掠夺者剥夺者 manga\t\t\t\t\t\t\t\tSeto Yu is a 12-year-old boy, that is abused violently by his father. One day, he is transported into a fantasy world with video game mechanics after being killed by his abusive father and he discovers that he has the unique ability to steal other people’s skills for his own use. He quickly uses his special power to take revenge on the townspeople who bully him and obtains a harem of beautiful girls who love him unconditionally even though he shows no romantic interest in any of them and has the physical build of a skinny teenager",
  "image": "https://imgjm.jmanga.ac/thumb/300/upload/2024/11/bbbf707b267d0804143e00f519ce0af1.jpeg",
  "related_manga": [
    {
      "url": "https://jmanga.se/read/奪う者-奪われる者-raw/",
      "title": "奪う者 奪われる者"
    },
    {
      "url": "https://jmanga.se/read/ヨメクラ-raw/",
      "title": "ヨメクラ"
    },
    {
      "url": "https://jmanga.se/read/じぇいけぇゆ-raw/",
      "title": "じぇいけぇゆ"
    },
    {
      "url": "https://jmanga.se/read/island-狂愛ⅹサバイバルー-raw/",
      "title": "ISLAND-狂愛ⅹサバイバルー"
    },
    {
      "url": "https://jmanga.se/read/fate-stay-night-heaven-s-feel-フェイト-ゼロ-raw/",
      "title": "Fate/stay night (Heaven?s Feel) フェイト/ゼロ"
    },
    {
      "url": "https://jmanga.se/read/faceless-ダークヒーロー編-raw/",
      "title": "faceless ? ダークヒーロー編"
    },
    {
      "url": "https://jmanga.se/read/変身したらヤリ放題！-マニアック・ウルフ-raw/",
      "title": "変身したらヤリ放題！ －マニアック・ウルフ－"
    },
    {
      "url": "https://jmanga.se/read/屍者の13月-raw/",
      "title": "屍者の13月"
    },
    {
      "url": "https://jmanga.se/read/gorse-ゴース-raw/",
      "title": "GORSE -ゴース"
    },
    {
      "url": "https://jmanga.se/read/どすこい！-すけひら-漫画-raw/",
      "title": "どすこい！　すけひら 漫画"
    },
    {
      "url": "https://jmanga.se/read/ディープ-インサニティー-raw/",
      "title": "ディープ インサニティー"
    },
    {
      "url": "https://jmanga.se/read/バーン・ザ・ウィッチ-raw/",
      "title": "バーン・ザ・ウィッチ"
    },
    {
      "url": "https://jmanga.se/read/ランドセルと異世界さんぽ-raw/",
      "title": "ランドセルと異世界さんぽ"
    },
    {
      "url": "https://jmanga.se/read/ベスティア-raw/",
      "title": "ベスティア"
    },
    {
      "url": "https://jmanga.se/read/hentai-清純お姫様のあまあま早漏改善特訓2-甘城ブリリアントパーク-raw/",
      "title": "Hentai ? 清純お姫様のあまあま早漏改善特訓2 (甘城ブリリアントパーク)"
    }
  ]
}