{
  "title": "機動戦士ガンダム外伝 ミッシングリンク",
  "short_title": "Missing Link",
  "chapter_count": 25,
  "url": "https://jmanga.io/read/機動戦士ガンダム外伝-ミッシングリンク-raw/",
  "genres": [
    "ヒューマンドラマ",
    "SF",
    "コミカライズ(小説・ゲーム)",
    "政治・ビジネス"
  ],
  "status": "",
  "summary": "機動戦士ガンダム外伝 ミッシングリンク raw,機動戦士ガンダム外伝 ミッシングリンク zip,機動戦士ガンダム外伝 ミッシングリンク manga\t\t\t\t\t\t\t\t激化する1年戦争の中、不正を働く連邦を粛正する影の部隊が存在した！バンダイナムコゲームスの大人気ゲーム「機動戦士ガンダム サイドストーリーズ」に収録された機動戦士ガンダム外伝ミッシングリンク、待望のコミカライズ第1巻！",
  "image": "https://imgjm.jmanga.ac/thumb/300/upload/2024/11/68d0ef293f7e7558c7a6ad9d2b3021ef.jpeg",
  "related_manga": [
    {
      "url": "https://jmanga.io/read/機動戦士ガンダム外伝-ザ・ブルー・ディスティニー-raw/",
      "title": "機動戦士ガンダム外伝 ザ・ブルー・ディスティニー"
    },
    {
      "url": "https://jmanga.io/read/我間乱～gamaran～-raw/",
      "title": "我間乱～GAMARAN～"
    },
    {
      "url": "https://jmanga.io/read/a-bout-～朝桐大活躍編～-raw/",
      "title": "A-BOUT!!～朝桐大活躍編～"
    },
    {
      "url": "https://jmanga.io/read/夜になると僕は-raw/",
      "title": "夜になると僕は"
    },
    {
      "url": "https://jmanga.io/read/this-man-その顔を見た者には死を-raw/",
      "title": "This Man その顔を見た者には死を"
    },
    {
      "url": "https://jmanga.io/read/エデンの檻-raw/",
      "title": "エデンの檻"
    },
    {
      "url": "https://jmanga.io/read/アンデッドガール・マーダーファルス-raw/",
      "title": "アンデッドガール・マーダーファルス"
    },
    {
      "url": "https://jmanga.io/read/線は、僕を描く-raw/",
      "title": "線は、僕を描く"
    },
    {
      "url": "https://jmanga.io/read/ふらちな倫理ちゃん-raw/",
      "title": "ふらちな倫理ちゃん"
    },
    {
      "url": "https://jmanga.io/read/やがて君になる-raw/",
      "title": "やがて君になる"
    },
    {
      "url": "https://jmanga.io/read/シバトラ-raw/",
      "title": "シバトラ"
    },
    {
      "url": "https://jmanga.io/read/trump-raw/",
      "title": "TRUMP"
    },
    {
      "url": "https://jmanga.io/read/はたらかない細胞-raw/",
      "title": "はたらかない細胞"
    },
    {
      "url": "https://jmanga.io/read/はたらく魔王さまのメシ！-raw/",
      "title": "はたらく魔王さまのメシ！"
    },
    {
      "url": "https://jmanga.io/read/仮面ライダーblack-raw/",
      "title": "仮面ライダーBlack"
    }
  ]
}