{
  "title": "もののけの乱",
  "short_title": "もののけの乱",
  "chapter_count": 22,
  "url": "https://jmanga.se/read/もののけの乱-raw/",
  "genres": [
    "バトル・アクション"
  ],
  "status": "",
  "summary": "もののけの乱 raw,もののけの乱 zip,もののけの乱 manga\t\t\t\t\t\t\t\t毎日、家に帰ると修行と称して祖父に襲いかかられる。そんなイカれた日常から脱したいと願う由緒正しき忍者の末裔・静 鵬一郎、高校1年生。平和な現代に、忍者は不要。いつものように忍者の後継から逃れるため、華の高校生活を犠牲にして一心不乱に勉学に邁進していたある日。鵬一郎を「運命の人」と訪ねてきた少女・御子神 今日花との出会いが彼の平和な日常を一変させる。忍者×陰陽師バディによる京都事件解決アクション開幕!!",
  "image": "https://imgjm.jmanga.ac/thumb/300/upload/2024/11/435ef383e709d7a42fbe5aad49132bbb.jpeg",
  "related_manga": [
    {
      "url": "https://jmanga.se/read/eat-man-the-main-dish-raw/",
      "title": "EAT-MAN THE MAIN DISH"
    },
    {
      "url": "https://jmanga.se/read/バカップル-raw/",
      "title": "バカップル"
    },
    {
      "url": "https://jmanga.se/read/拳児２-raw/",
      "title": "拳児２"
    },
    {
      "url": "https://jmanga.se/read/寄宿学校のジュリエット-raw/",
      "title": "寄宿学校のジュリエット"
    },
    {
      "url": "https://jmanga.se/read/エデンの檻-raw/",
      "title": "エデンの檻"
    },
    {
      "url": "https://jmanga.se/read/とんずらごはん-raw/",
      "title": "とんずらごはん"
    },
    {
      "url": "https://jmanga.se/read/恋ニ非ズ-raw/",
      "title": "恋ニ非ズ"
    },
    {
      "url": "https://jmanga.se/read/ゆこさえ戦えば-raw/",
      "title": "ゆこさえ戦えば"
    },
    {
      "url": "https://jmanga.se/read/吸血鬼ちゃんx後輩ちゃん-raw/",
      "title": "吸血鬼ちゃん×後輩ちゃん"
    },
    {
      "url": "https://jmanga.se/read/シバトラ-raw/",
      "title": "シバトラ"
    },
    {
      "url": "https://jmanga.se/read/やがて君になる-raw/",
      "title": "やがて君になる"
    },
    {
      "url": "https://jmanga.se/read/夜になると僕は-raw/",
      "title": "夜になると僕は"
    },
    {
      "url": "https://jmanga.se/read/死なないで！明日川さん-raw/",
      "title": "死なないで！明日川さん"
    },
    {
      "url": "https://jmanga.se/read/trump-raw/",
      "title": "TRUMP"
    },
    {
      "url": "https://jmanga.se/read/a-bout-～朝桐大活躍編～-raw/",
      "title": "A-BOUT!!～朝桐大活躍編～"
    }
  ]
}