{
  "title": "アラフィフ！",
  "short_title": "アラフィフ",
  "chapter_count": 8,
  "url": "https://jmanga.io/read/アラフィフ！-raw/",
  "genres": [
    "ギャグ・コメディー",
    "4コマ",
    "ルポ・エッセイ"
  ],
  "status": "",
  "summary": "アラフィフ！ raw,アラフィフ！ zip,アラフィフ！ manga\t\t\t\t\t\t\t\t祖母・嫁・孫の三世帯同居コメディ！主人公はまさかの祖母55歳！\nある日突然同居することになった祖母は、ちょっと変な格好をした昭和育ちの昭和世代。\n一方、嫁はコンビニ店長35歳、、孫はJK15歳。人世代ずつずれた三人の日常を描くマンガをよろしく！",
  "image": "https://imgjm.jmanga.ac/thumb/300/upload/2024/11/984cc8cf4d8d1c048d844dc18a9933ad.jpeg",
  "related_manga": [
    {
      "url": "https://jmanga.io/read/とんずらごはん-raw/",
      "title": "とんずらごはん"
    },
    {
      "url": "https://jmanga.io/read/this-man-その顔を見た者には死を-raw/",
      "title": "This Man その顔を見た者には死を"
    },
    {
      "url": "https://jmanga.io/read/コンビニお嬢さま-raw/",
      "title": "コンビニお嬢さま"
    },
    {
      "url": "https://jmanga.io/read/拳児２-raw/",
      "title": "拳児２"
    },
    {
      "url": "https://jmanga.io/read/はたらかない細胞-raw/",
      "title": "はたらかない細胞"
    },
    {
      "url": "https://jmanga.io/read/吸血鬼ちゃんx後輩ちゃん-raw/",
      "title": "吸血鬼ちゃん×後輩ちゃん"
    },
    {
      "url": "https://jmanga.io/read/紅殻のパンドラ-raw/",
      "title": "紅殻のパンドラ"
    },
    {
      "url": "https://jmanga.io/read/寄宿学校のジュリエット-raw/",
      "title": "寄宿学校のジュリエット"
    },
    {
      "url": "https://jmanga.io/read/生きとし生ける-raw/",
      "title": "生きとし生ける"
    },
    {
      "url": "https://jmanga.io/read/おやすみ睡魔と夜ふかしjk-raw/",
      "title": "おやすみ睡魔と夜ふかしJK"
    },
    {
      "url": "https://jmanga.io/read/恋ニ非ズ-raw/",
      "title": "恋ニ非ズ"
    },
    {
      "url": "https://jmanga.io/read/夜になると僕は-raw/",
      "title": "夜になると僕は"
    },
    {
      "url": "https://jmanga.io/read/eat-man-the-main-dish-raw/",
      "title": "EAT-MAN THE MAIN DISH"
    },
    {
      "url": "https://jmanga.io/read/開演のベルでおやすみ-raw/",
      "title": "開演のベルでおやすみ"
    },
    {
      "url": "https://jmanga.io/read/落ちてるふたり-raw/",
      "title": "落ちてるふたり"
    }
  ]
}