{
  "title": "ボクが勇者で魔王もボクで",
  "short_title": "ボクが勇者",
  "chapter_count": 22,
  "url": "https://jmanga.io/read/ボクが勇者で魔王もボクで-raw/",
  "genres": [
    "異世界・転生",
    "ギャグ・コメディー"
  ],
  "status": "",
  "summary": "ボクが勇者で魔王もボクで raw,ボクが勇者で魔王もボクで zip,ボクが勇者で魔王もボクで manga\t\t\t\t\t\t\t\t時空とかいろいろ越えた勇者×魔王の伝説がここに!! 異世界⇔お茶の間ぐだぐだコメディ開幕！ 津狩優真は平凡な高校生。下町の銭湯の息子として平和な日々を送る……ハズだったのだが、ある日突然異世界から来訪者が現れて――。美少女たちの猛アプローチに、優真はいったいどうなってしまうのか!?",
  "image": "https://imgjm.jmanga.ac/thumb/300/upload/2024/11/959fb1d02a199573ea71d039f3a56e48.jpeg",
  "related_manga": [
    {
      "url": "https://jmanga.io/read/夜になると僕は-raw/",
      "title": "夜になると僕は"
    },
    {
      "url": "https://jmanga.io/read/乙女高校ボクシング部-raw/",
      "title": "乙女高校ボクシング部"
    },
    {
      "url": "https://jmanga.io/read/線は、僕を描く-raw/",
      "title": "線は、僕を描く"
    },
    {
      "url": "https://jmanga.io/read/ゆこさえ戦えば-raw/",
      "title": "ゆこさえ戦えば"
    },
    {
      "url": "https://jmanga.io/read/とんずらごはん-raw/",
      "title": "とんずらごはん"
    },
    {
      "url": "https://jmanga.io/read/コンビニお嬢さま-raw/",
      "title": "コンビニお嬢さま"
    },
    {
      "url": "https://jmanga.io/read/エデンの檻-raw/",
      "title": "エデンの檻"
    },
    {
      "url": "https://jmanga.io/read/恋ニ非ズ-raw/",
      "title": "恋ニ非ズ"
    },
    {
      "url": "https://jmanga.io/read/アンデッドガール・マーダーファルス-raw/",
      "title": "アンデッドガール・マーダーファルス"
    },
    {
      "url": "https://jmanga.io/read/ふらちな倫理ちゃん-raw/",
      "title": "ふらちな倫理ちゃん"
    },
    {
      "url": "https://jmanga.io/read/寄宿学校のジュリエット-raw/",
      "title": "寄宿学校のジュリエット"
    },
    {
      "url": "https://jmanga.io/read/落ちてるふたり-raw/",
      "title": "落ちてるふたり"
    },
    {
      "url": "https://jmanga.io/read/拳児２-raw/",
      "title": "拳児２"
    },
    {
      "url": "https://jmanga.io/read/紅殻のパンドラ-raw/",
      "title": "紅殻のパンドラ"
    },
    {
      "url": "https://jmanga.io/read/シバトラ-raw/",
      "title": "シバトラ"
    }
  ]
}