{
  "title": "侯爵令嬢の借金執事",
  "short_title": "侯爵令嬢",
  "chapter_count": 19,
  "url": "https://jmanga.se/read/侯爵令嬢の借金執事-raw/",
  "genres": [
    "ファンタジー",
    "SF"
  ],
  "status": "",
  "summary": "侯爵令嬢の借金執事 raw,侯爵令嬢の借金執事 zip,侯爵令嬢の借金執事 manga\t\t\t\t\t\t\t\tアークライト男爵家の三男・ジャックはある日、父がロードランド侯爵家から多額の借金をしていたことが発覚する。父の借金のかた、そして祖父と先代侯爵の遺した誓約によりジャックは侯爵令嬢・エミリアの“許嫁”兼“執事”となってしまうことに…！ツンデレお嬢様×借金執事の甘々すれ違いお屋敷同居生活スタート！",
  "image": "https://imgjm.jmanga.ac/thumb/300/upload/2024/11/a97ab7065ea0b3d53b9c7bb5180102a1.jpeg",
  "related_manga": [
    {
      "url": "https://jmanga.se/read/高校事変-raw/",
      "title": "高校事変"
    },
    {
      "url": "https://jmanga.se/read/やきもの九十九の素敵な食卓-raw/",
      "title": "やきもの九十九の素敵な食卓"
    },
    {
      "url": "https://jmanga.se/read/小林少年と不逞の怪人-raw/",
      "title": "小林少年と不逞の怪人"
    },
    {
      "url": "https://jmanga.se/read/育てち魔おう！-raw/",
      "title": "育てち魔おう！"
    },
    {
      "url": "https://jmanga.se/read/小さいノゾミと大きなユメ-raw/",
      "title": "小さいノゾミと大きなユメ"
    },
    {
      "url": "https://jmanga.se/read/あやかしメルヒェン-raw/",
      "title": "あやかしメルヒェン"
    },
    {
      "url": "https://jmanga.se/read/はじめしゃちょーのユーチューバーな日常-raw/",
      "title": "はじめしゃちょーのユーチューバーな日常"
    },
    {
      "url": "https://jmanga.se/read/金田一３７歳の事件簿-raw/",
      "title": "金田一３７歳の事件簿"
    },
    {
      "url": "https://jmanga.se/read/ホームルーム-raw/",
      "title": "ホームルーム"
    },
    {
      "url": "https://jmanga.se/read/鳴かせてくれない上家さん-raw/",
      "title": "鳴かせてくれない上家さん"
    },
    {
      "url": "https://jmanga.se/read/ひのきのダンジョン-raw/",
      "title": "ひのきのダンジョン"
    },
    {
      "url": "https://jmanga.se/read/魔女の守人-raw/",
      "title": "魔女の守人"
    },
    {
      "url": "https://jmanga.se/read/大蜘蛛ちゃんフラッシュ・バック-raw/",
      "title": "大蜘蛛ちゃんフラッシュ・バック"
    },
    {
      "url": "https://jmanga.se/read/だから僕達は幼馴染を辞めた。-raw/",
      "title": "だから僕達は幼馴染を辞めた。"
    },
    {
      "url": "https://jmanga.se/read/友達として大好き-raw/",
      "title": "友達として大好き"
    }
  ]
}