{
  "title": "富嶽百景グラフィアトル",
  "short_title": "",
  "chapter_count": 4,
  "url": "https://jmanga.se/read/富嶽百景グラフィアトル-raw/",
  "genres": [
    "ロマンス"
  ],
  "status": "",
  "summary": "富嶽百景グラフィアトル raw,富嶽百景グラフィアトル zip,富嶽百景グラフィアトル manga\t\t\t\t\t\t\t\tFugaku Hyaku Kei Graph Iatoru Raw\n\n時は文慶3年。絵画統制に反対する倒幕派の末裔集団と警察組織・式隊による「画芸」バトルが激化していた。画芸とは、自分が思い描いた絵を形にする力。絵の出来はイマイチだが、都の人々を守りたいという熱い思いと画芸の自由を希う心で、淡雪は式隊に入隊する。しかし、相棒はクールで才能豊かな紅輝で……。俺は一人でいい。俺は一人でいい、俺の力が必要なのはお前だけだ。相棒同士の幕末画芸バトル、開幕！最高に尊い！原作小説コンテストバディ部門大賞受賞作。",
  "image": "https://imgjm.jmanga.ac/thumb/300/upload/2025/03/5ab11cd0eba01424769a3fe893ac5c3e.jpeg",
  "related_manga": [
    {
      "url": "https://jmanga.se/read/二ノ国-～光の後継者と猫の王子～-raw/",
      "title": "二ノ国 ～光の後継者と猫の王子～"
    },
    {
      "url": "https://jmanga.se/read/final-re-quest-ファイナルリクエスト-raw/",
      "title": "Final Re:Quest ―ファイナルリクエスト―"
    },
    {
      "url": "https://jmanga.se/read/スキル『台所召喚』はすごい！～異世界でごはん作ってポイントためます～-raw/",
      "title": "スキル『台所召喚』はすごい！～異世界でごはん作ってポイントためます～"
    },
    {
      "url": "https://jmanga.se/read/魔法少年は、愛液で世界を救う。-raw/",
      "title": "魔法少年は、愛液で世界を救う。"
    },
    {
      "url": "https://jmanga.se/read/island-狂愛ⅹサバイバルー-raw/",
      "title": "ISLAND-狂愛ⅹサバイバルー"
    },
    {
      "url": "https://jmanga.se/read/パーフェクト・ガール-raw/",
      "title": "パーフェクト・ガール"
    },
    {
      "url": "https://jmanga.se/read/ポンコツンデレな幼馴染-raw/",
      "title": "ポンコツンデレな幼馴染"
    },
    {
      "url": "https://jmanga.se/read/殿さまとスティッチ-raw/",
      "title": "殿さまとスティッチ"
    },
    {
      "url": "https://jmanga.se/read/フェアリーテイル-１００年クエスト-raw/",
      "title": "フェアリーテイル １００年クエスト"
    },
    {
      "url": "https://jmanga.se/read/ヨメクラ-raw/",
      "title": "ヨメクラ"
    },
    {
      "url": "https://jmanga.se/read/hentai-清純お姫様のあまあま早漏改善特訓2-甘城ブリリアントパーク-raw/",
      "title": "Hentai ? 清純お姫様のあまあま早漏改善特訓2 (甘城ブリリアントパーク)"
    },
    {
      "url": "https://jmanga.se/read/ランドセルと異世界さんぽ-raw/",
      "title": "ランドセルと異世界さんぽ"
    },
    {
      "url": "https://jmanga.se/read/ディープ-インサニティー-raw/",
      "title": "ディープ インサニティー"
    },
    {
      "url": "https://jmanga.se/read/イミグリム-～弱虫悪魔の異世界移住計画～-raw/",
      "title": "イミグリム ～弱虫悪魔の異世界移住計画～"
    },
    {
      "url": "https://jmanga.se/read/むさしの新聞日記-raw/",
      "title": "むさしの新聞日記"
    }
  ]
}