{
  "title": "身体は児童、中身はおっさんの成り上がり冒険記 サテラもついて行きます！",
  "short_title": "",
  "chapter_count": 15,
  "url": "https://jmanga.se/read/身体は児童、中身はおっさんの成り上がり冒険記-サテラもついて行きます！-raw/",
  "genres": [
    "ファンタジー"
  ],
  "status": "",
  "summary": "身体は児童、中身はおっさんの成り上がり冒険記 サテラもついて行きます！ raw,身体は児童、中身はおっさんの成り上がり冒険記 サテラもついて行きます！ zip,身体は児童、中身はおっさんの成り上がり冒険記 サテラもついて行きます！ manga\t\t\t\t\t\t\t\tKarada wa Jido, Nakami wa Ossan no Nariagari Bokenki Satera mo Tsuiteikimasu! Raw\n\n貧乏領地で病床の祖父と暮らすサテラ。\nある日、領主の息子・グレイの捜索命令が出たと聞き、サテラは捜し出したお礼に祖父を治してもらおうと森へ向かう。\nしかし、そこには魔物が巣くっており、ようやくグレイを見つけ出すが…。\n\n大人気小説をサテラ視点で新たにコミカライズ！\n異世界冒険ファンタジー!!",
  "image": "https://imgjm.jmanga.ac/thumb/300/upload/2025/03/37a0bba644c8fd6d94918e960a24de92.jpeg",
  "related_manga": [
    {
      "url": "https://jmanga.se/read/身体は児童、中身はおっさんの成り上がり冒険記-raw/",
      "title": "身体は児童、中身はおっさんの成り上がり冒険記"
    },
    {
      "url": "https://jmanga.se/read/gorse-ゴース-raw/",
      "title": "GORSE -ゴース"
    },
    {
      "url": "https://jmanga.se/read/ベスティア-raw/",
      "title": "ベスティア"
    },
    {
      "url": "https://jmanga.se/read/むさしの新聞日記-raw/",
      "title": "むさしの新聞日記"
    },
    {
      "url": "https://jmanga.se/read/名古屋以外全部壊滅-raw/",
      "title": "名古屋以外全部壊滅"
    },
    {
      "url": "https://jmanga.se/read/色即是空の歩き方-raw/",
      "title": "色即是空の歩き方"
    },
    {
      "url": "https://jmanga.se/read/ヨメクラ-raw/",
      "title": "ヨメクラ"
    },
    {
      "url": "https://jmanga.se/read/island-狂愛ⅹサバイバルー-raw/",
      "title": "ISLAND-狂愛ⅹサバイバルー"
    },
    {
      "url": "https://jmanga.se/read/ポンコツンデレな幼馴染-raw/",
      "title": "ポンコツンデレな幼馴染"
    },
    {
      "url": "https://jmanga.se/read/hentai-清純お姫様のあまあま早漏改善特訓2-甘城ブリリアントパーク-raw/",
      "title": "Hentai ? 清純お姫様のあまあま早漏改善特訓2 (甘城ブリリアントパーク)"
    },
    {
      "url": "https://jmanga.se/read/スキル『台所召喚』はすごい！～異世界でごはん作ってポイントためます～-raw/",
      "title": "スキル『台所召喚』はすごい！～異世界でごはん作ってポイントためます～"
    },
    {
      "url": "https://jmanga.se/read/無法鳥-raw/",
      "title": "無法鳥"
    },
    {
      "url": "https://jmanga.se/read/キン肉マン-38巻以降-、週プレ連載シリーズ-raw/",
      "title": "キン肉マン (38巻以降〜、週プレ連載シリーズ)"
    },
    {
      "url": "https://jmanga.se/read/じぇいけぇゆ-raw/",
      "title": "じぇいけぇゆ"
    },
    {
      "url": "https://jmanga.se/read/ストーカー浄化団-stalker-jokers-raw/",
      "title": "ストーカー浄化団 -STALKER JOKERS"
    }
  ]
}