{
  "title": "閻魔様の仰せのまま",
  "short_title": "閻魔様の仰せ",
  "chapter_count": 154,
  "url": "https://jmanga.se/read/閻魔様の仰せのまま-raw/",
  "genres": [
    "ファンタジー",
    "フルカラー",
    "転生",
    "女性マンガ",
    "独占配信",
    "SMARTOON",
    "NCOMIC"
  ],
  "status": "",
  "summary": "",
  "image": "https://imgjm.jmanga.ac/thumb/300/upload/2024/11/aa3ca1faf9d27991d012cc887d2b2b5c.jpeg",
  "related_manga": [
    {
      "url": "https://jmanga.se/read/名古屋以外全部壊滅-raw/",
      "title": "名古屋以外全部壊滅"
    },
    {
      "url": "https://jmanga.se/read/final-re-quest-ファイナルリクエスト-raw/",
      "title": "Final Re:Quest ―ファイナルリクエスト―"
    },
    {
      "url": "https://jmanga.se/read/fate-stay-night-heaven-s-feel-フェイト-ゼロ-raw/",
      "title": "Fate/stay night (Heaven?s Feel) フェイト/ゼロ"
    },
    {
      "url": "https://jmanga.se/read/無法鳥-raw/",
      "title": "無法鳥"
    },
    {
      "url": "https://jmanga.se/read/どすこい！-すけひら-漫画-raw/",
      "title": "どすこい！　すけひら 漫画"
    },
    {
      "url": "https://jmanga.se/read/色即是空の歩き方-raw/",
      "title": "色即是空の歩き方"
    },
    {
      "url": "https://jmanga.se/read/ストーカー浄化団-stalker-jokers-raw/",
      "title": "ストーカー浄化団 -STALKER JOKERS"
    },
    {
      "url": "https://jmanga.se/read/ヨメクラ-raw/",
      "title": "ヨメクラ"
    },
    {
      "url": "https://jmanga.se/read/バーン・ザ・ウィッチ-raw/",
      "title": "バーン・ザ・ウィッチ"
    },
    {
      "url": "https://jmanga.se/read/gorse-ゴース-raw/",
      "title": "GORSE -ゴース"
    },
    {
      "url": "https://jmanga.se/read/ポンコツンデレな幼馴染-raw/",
      "title": "ポンコツンデレな幼馴染"
    },
    {
      "url": "https://jmanga.se/read/殿さまとスティッチ-raw/",
      "title": "殿さまとスティッチ"
    },
    {
      "url": "https://jmanga.se/read/魔法少年は、愛液で世界を救う。-raw/",
      "title": "魔法少年は、愛液で世界を救う。"
    },
    {
      "url": "https://jmanga.se/read/変身したらヤリ放題！-マニアック・ウルフ-raw/",
      "title": "変身したらヤリ放題！ －マニアック・ウルフ－"
    },
    {
      "url": "https://jmanga.se/read/イミグリム-～弱虫悪魔の異世界移住計画～-raw/",
      "title": "イミグリム ～弱虫悪魔の異世界移住計画～"
    }
  ]
}