{
  "title": "ハレ婚。おかわり！",
  "short_title": "ハレ婚",
  "chapter_count": 8,
  "url": "https://jmanga.se/read/ハレ婚。おかわり！-raw/",
  "genres": [
    "Ecchi",
    "ロマンス",
    "恋愛"
  ],
  "status": "",
  "summary": "ハレ婚。おかわり！ raw,ハレ婚。おかわり！ zip,ハレ婚。おかわり！ manga\t\t\t\t\t\t\t\t累計260万部超&ドラマ化！一夫多妻制を描いた衝撃作『ハレ婚。』が帰ってきた！",
  "image": "https://imgjm.jmanga.ac/thumb/300/upload/2024/11/acf66c3a07f45572623388f4bfb58f09.jpeg",
  "related_manga": [
    {
      "url": "https://jmanga.se/read/ハレ婚。-raw/",
      "title": "ハレ婚。"
    },
    {
      "url": "https://jmanga.se/read/僕らの食卓-～おかわり～-raw/",
      "title": "僕らの食卓 ～おかわり～"
    },
    {
      "url": "https://jmanga.se/read/アキはハルとごはんを食べたい-おかわり！-raw/",
      "title": "アキはハルとごはんを食べたい おかわり！"
    },
    {
      "url": "https://jmanga.se/read/じぇいけぇゆ-raw/",
      "title": "じぇいけぇゆ"
    },
    {
      "url": "https://jmanga.se/read/イミグリム-～弱虫悪魔の異世界移住計画～-raw/",
      "title": "イミグリム ～弱虫悪魔の異世界移住計画～"
    },
    {
      "url": "https://jmanga.se/read/屍者の13月-raw/",
      "title": "屍者の13月"
    },
    {
      "url": "https://jmanga.se/read/ディープ-インサニティー-raw/",
      "title": "ディープ インサニティー"
    },
    {
      "url": "https://jmanga.se/read/どすこい！-すけひら-漫画-raw/",
      "title": "どすこい！　すけひら 漫画"
    },
    {
      "url": "https://jmanga.se/read/無法鳥-raw/",
      "title": "無法鳥"
    },
    {
      "url": "https://jmanga.se/read/変身したらヤリ放題！-マニアック・ウルフ-raw/",
      "title": "変身したらヤリ放題！ －マニアック・ウルフ－"
    },
    {
      "url": "https://jmanga.se/read/バーン・ザ・ウィッチ-raw/",
      "title": "バーン・ザ・ウィッチ"
    },
    {
      "url": "https://jmanga.se/read/色即是空の歩き方-raw/",
      "title": "色即是空の歩き方"
    },
    {
      "url": "https://jmanga.se/read/gorse-ゴース-raw/",
      "title": "GORSE -ゴース"
    },
    {
      "url": "https://jmanga.se/read/island-狂愛ⅹサバイバルー-raw/",
      "title": "ISLAND-狂愛ⅹサバイバルー"
    },
    {
      "url": "https://jmanga.se/read/faceless-ダークヒーロー編-raw/",
      "title": "faceless ? ダークヒーロー編"
    }
  ]
}