{
  "title": "天空の城をもらったので異世界で楽しく遊びたい",
  "short_title": "天空の城",
  "chapter_count": 50,
  "url": "https://jmanga.io/read/天空の城をもらったので異世界で楽しく遊びたい-raw/",
  "genres": [
    "ファンタジー",
    "異世界・転生"
  ],
  "status": "",
  "summary": "天空の城をもらったので異世界で楽しく遊びたい raw,天空の城をもらったので異世界で楽しく遊びたい zip,天空の城をもらったので異世界で楽しく遊びたい manga\t\t\t\t\t\t\t\t青年・椎原大希は天使の手違いにより、命を落としてしまう。お詫びに、一つだけ願いを叶えたうえで、異世界へと転生させられることに。\nタイキが望んだのは――天空の城。\n目を覚ますと、異世界の空に浮かび、ドラゴンにも破られない強力な防御結界を持ち、数多のゴーレムを配備し、そして、生活設備の整った最強の空中要塞の主となっていた！",
  "image": "https://imgjm.jmanga.ac/thumb/300/upload/2024/11/d92609d1f3557168db2623b8a12ab8fc.jpeg",
  "related_manga": [
    {
      "url": "https://jmanga.io/read/開演のベルでおやすみ-raw/",
      "title": "開演のベルでおやすみ"
    },
    {
      "url": "https://jmanga.io/read/我間乱～gamaran～-raw/",
      "title": "我間乱～GAMARAN～"
    },
    {
      "url": "https://jmanga.io/read/アンデッドガール・マーダーファルス-raw/",
      "title": "アンデッドガール・マーダーファルス"
    },
    {
      "url": "https://jmanga.io/read/夜になると僕は-raw/",
      "title": "夜になると僕は"
    },
    {
      "url": "https://jmanga.io/read/コンビニお嬢さま-raw/",
      "title": "コンビニお嬢さま"
    },
    {
      "url": "https://jmanga.io/read/trump-raw/",
      "title": "TRUMP"
    },
    {
      "url": "https://jmanga.io/read/バカップル-raw/",
      "title": "バカップル"
    },
    {
      "url": "https://jmanga.io/read/紅殻のパンドラ-raw/",
      "title": "紅殻のパンドラ"
    },
    {
      "url": "https://jmanga.io/read/eat-man-the-main-dish-raw/",
      "title": "EAT-MAN THE MAIN DISH"
    },
    {
      "url": "https://jmanga.io/read/やがて君になる-raw/",
      "title": "やがて君になる"
    },
    {
      "url": "https://jmanga.io/read/はたらく魔王さまのメシ！-raw/",
      "title": "はたらく魔王さまのメシ！"
    },
    {
      "url": "https://jmanga.io/read/this-man-その顔を見た者には死を-raw/",
      "title": "This Man その顔を見た者には死を"
    },
    {
      "url": "https://jmanga.io/read/とんずらごはん-raw/",
      "title": "とんずらごはん"
    },
    {
      "url": "https://jmanga.io/read/拳児２-raw/",
      "title": "拳児２"
    },
    {
      "url": "https://jmanga.io/read/a-bout-～朝桐大活躍編～-raw/",
      "title": "A-BOUT!!～朝桐大活躍編～"
    }
  ]
}